taylorswift/Grades.csv
taylorswift/__init__.py
taylorswift/answertext.txt
taylorswift/main.py
taylorswift/version.py
taylorswift-0.1.1rc1.dist-info/LICENSE.txt
taylorswift-0.1.1rc1.dist-info/METADATA
taylorswift-0.1.1rc1.dist-info/WHEEL
taylorswift-0.1.1rc1.dist-info/top_level.txt
taylorswift-0.1.1rc1.dist-info/RECORD
